mailtransport/__init__.py
mailtransport/core.py
mailtransport/exeptions.py
mailtransport/identity.py
mailtransport/mail.py
mailtransport-0.1.5.dist-info/LICENSE
mailtransport-0.1.5.dist-info/METADATA
mailtransport-0.1.5.dist-info/WHEEL
mailtransport-0.1.5.dist-info/top_level.txt
mailtransport-0.1.5.dist-info/RECORD
