Metadata-Version: 2.1
Name: mailtransport
Version: 0.1.5
Summary: A Python package for managing email transport.
Home-page: https://github.com/mailtransportai/mailtransport-py
Author: mailtransportai
Author-email: support@mailtransportai.com
License: MIT
Classifier: Programming Language :: Python :: 3
Classifier: License :: OSI Approved :: MIT License
Classifier: Operating System :: OS Independent
Requires-Python: >=3.6
License-File: LICENSE
Requires-Dist: requests
